auto_switch_providers/__init__.py
auto_switch_providers/__version__.py
auto_switch_providers/auto_switch_providers.py
auto_switch_providers/cache_service.py
auto_switch_providers/http_service.py
auto_switch_providers/services/__init__.py
auto_switch_providers/services/redis_service.py
auto_switch_providers/utils/__init__.py
auto_switch_providers/utils/helpers.py
auto_switch_providers-0.0.8.dist-info/LICENSE
auto_switch_providers-0.0.8.dist-info/METADATA
auto_switch_providers-0.0.8.dist-info/WHEEL
auto_switch_providers-0.0.8.dist-info/top_level.txt
auto_switch_providers-0.0.8.dist-info/RECORD
